[{"id":2,"nombre":"Poye So10r 656j","costoEstimadoInicial":600000.0,"inversion":5.0,"fechaInicio":"2023-05-01","fechaFin":"2024-11-01","tiempoDeVida":25,"capacidad":22,"tipoEnergia":"SOLAR","ubicacion":"LOJA","descripcion":"Proyecto de energía solar en Loja","estado":"FINALIZADO"},{"id":3,"nombre":"Poye So10r 656j","costoEstimadoInicial":5000000.0,"inversion":1.0E26,"fechaInicio":"2023-05-01","fechaFin":"2023-05-01","tiempoDeVida":25,"capacidad":0,"tipoEnergia":"SOLAR","ubicacion":"LOJA","descripcion":"Proyecto de energía solar en Loja","estado":"FINALIZADO"},{"id":2,"nombre":"Poye So10r 656j","costoEstimadoInicial":600000.0,"inversion":1.0E26,"fechaInicio":"2023-05-01","fechaFin":"2024-11-01","tiempoDeVida":25,"capacidad":22,"tipoEnergia":"SOLAR","ubicacion":"LOJA","descripcion":"Proyecto de energía solar en Loja","estado":"FINALIZADO"},{"id":5,"nombre":"Poye So10r 656j","costoEstimadoInicial":5000000.0,"inversion":0.0,"fechaInicio":"2023-05-01","tiempoDeVida":25,"capacidad":0,"tipoEnergia":"SOLAR","ubicacion":"LOJA","descripcion":"Proyecto de energía solar en Loja","estado":"FINALIZADO"},{"id":6,"nombre":"Poye So10r 656j","costoEstimadoInicial":5000000.0,"inversion":350.0,"fechaInicio":"2023-05-01","tiempoDeVida":25,"capacidad":150,"tipoEnergia":"SOLAR","ubicacion":"LOJA","descripcion":"Proyecto de energía solar en Loja","estado":"FINALIZADO"},{"id":8,"nombre":"Hola men So10r 656j","costoEstimadoInicial":655.0,"inversion":55.0,"fechaInicio":"2023-05-01","tiempoDeVida":25,"capacidad":0,"tipoEnergia":"SOLAR","ubicacion":"LOJA","descripcion":"Proyecto de energía solar en Loja","estado":"FINALIZADO"},{"id":9,"nombre":"Poye","costoEstimadoInicial":5000000.0,"inversion":1111.0,"fechaInicio":"2023-05-01","tiempoDeVida":25,"capacidad":0,"tipoEnergia":"SOLAR","ubicacion":"LOJA","descripcion":"Proyecto de energía solar en Loja","estado":"FINALIZADO"},{"id":10,"nombre":"Poye","costoEstimadoInicial":5000000.0,"inversion":0.0,"fechaInicio":"2023-05-01","tiempoDeVida":25,"capacidad":0,"tipoEnergia":"SOLAR","ubicacion":"LOJA","descripcion":"Proyecto de energía solar en Loja","estado":"FINALIZADO"},{"id":11,"nombre":"Poye","costoEstimadoInicial":5000000.0,"inversion":0.0,"fechaInicio":"2023-05-01","tiempoDeVida":25,"capacidad":0,"tipoEnergia":"SOLAR","ubicacion":"LOJA","descripcion":"Proyecto de energía solar en Loja","estado":"FINALIZADO"},{"id":12,"nombre":"Poye","costoEstimadoInicial":5000000.0,"inversion":0.0,"fechaInicio":"2023-05-01","tiempoDeVida":25,"capacidad":0,"tipoEnergia":"SOLAR","ubicacion":"LOJA","descripcion":"Proyecto de energía solar en Loja","estado":"FINALIZADO"},{"id":13,"nombre":"Poye","costoEstimadoInicial":5000000.0,"inversion":0.0,"fechaInicio":"2023-05-01","tiempoDeVida":25,"capacidad":0,"tipoEnergia":"SOLAR","ubicacion":"LOJA","descripcion":"Proyecto de energía solar en Loja","estado":"FINALIZADO"},{"id":14,"nombre":"Poye","costoEstimadoInicial":5000000.0,"inversion":0.0,"fechaInicio":"2023-05-01","tiempoDeVida":25,"capacidad":0,"tipoEnergia":"SOLAR","ubicacion":"LOJA","descripcion":"Proyecto de energía solar en Loja","estado":"FINALIZADO"},{"id":15,"nombre":"Poye","costoEstimadoInicial":5000000.0,"inversion":0.0,"fechaInicio":"2023-05-01","tiempoDeVida":25,"capacidad":0,"tipoEnergia":"SOLAR","ubicacion":"LOJA","descripcion":"Proyecto de energía solar en Loja","estado":"FINALIZADO"},{"id":16,"nombre":"Poye","costoEstimadoInicial":5000000.0,"inversion":0.0,"fechaInicio":"2023-05-01","tiempoDeVida":25,"capacidad":0,"tipoEnergia":"SOLAR","ubicacion":"LOJA","descripcion":"Proyecto de energía solar en Loja","estado":"FINALIZADO"},{"id":17,"nombre":"Poye","costoEstimadoInicial":5000000.0,"inversion":0.0,"fechaInicio":"2023-05-01","tiempoDeVida":25,"capacidad":0,"tipoEnergia":"SOLAR","ubicacion":"LOJA","descripcion":"Proyecto de energía solar en Loja","estado":"FINALIZADO"},{"id":18,"nombre":"Poye","costoEstimadoInicial":5000000.0,"inversion":0.0,"fechaInicio":"2023-05-01","tiempoDeVida":25,"capacidad":0,"tipoEnergia":"SOLAR","ubicacion":"LOJA","descripcion":"Proyecto de energía solar en Loja","estado":"FINALIZADO"},{"id":19,"nombre":"Poye","costoEstimadoInicial":5000000.0,"inversion":0.0,"fechaInicio":"2023-05-01","tiempoDeVida":25,"capacidad":0,"tipoEnergia":"SOLAR","ubicacion":"LOJA","descripcion":"Proyecto de energía solar en Loja","estado":"FINALIZADO"},{"id":20,"nombre":"Poye","costoEstimadoInicial":5000000.0,"inversion":0.0,"fechaInicio":"2023-05-01","tiempoDeVida":25,"capacidad":0,"tipoEnergia":"SOLAR","ubicacion":"LOJA","descripcion":"Proyecto de energía solar en Loja","estado":"FINALIZADO"},{"id":21,"nombre":"dasda","costoEstimadoInicial":10000.0,"inversion":0.0,"fechaInicio":"2024-11-01","tiempoDeVida":11,"capacidad":11,"tipoEnergia":"SOLAR","ubicacion":"AZUAY","descripcion":"asdasd","estado":"PLANTEADO"},{"id":22,"nombre":"qweqwe","costoEstimadoInicial":1000.0,"inversion":0.0,"fechaInicio":"2024-11-01","tiempoDeVida":111,"capacidad":111,"tipoEnergia":"SOLAR","ubicacion":"AZUAY","descripcion":"qweqwe","estado":"PLANTEADO"},{"id":23,"nombre":"qweqwe","costoEstimadoInicial":1000.0,"inversion":0.0,"fechaInicio":"2024-11-01","tiempoDeVida":111,"capacidad":111,"tipoEnergia":"SOLAR","ubicacion":"AZUAY","descripcion":"qweqwe","estado":"PLANTEADO"},{"id":25,"nombre":"aasd","costoEstimadoInicial":12122.0,"inversion":0.0,"fechaInicio":"2024-11-01","tiempoDeVida":111,"capacidad":1111,"tipoEnergia":"SOLAR","ubicacion":"AZUAY","descripcion":"asdasd","estado":"PLANTEADO"},{"id":26,"nombre":"adasd","costoEstimadoInicial":121.0,"inversion":745.0,"fechaInicio":"2024-11-01","fechaFin":"2024-11-01","tiempoDeVida":11,"capacidad":11,"tipoEnergia":"SOLAR","ubicacion":"AZUAY","descripcion":"asdasd","estado":"PLANTEADO"}]